MANIFEST.in
README.md
requirements-dev.txt
requirements.txt
setup.py
tictail/__init__.py
tictail/client.py
tictail/errors.py
tictail/importer.py
tictail/transport.py
tictail/version.py
tictail.egg-info/PKG-INFO
tictail.egg-info/SOURCES.txt
tictail.egg-info/dependency_links.txt
tictail.egg-info/requires.txt
tictail.egg-info/top_level.txt
tictail/resource/__init__.py
tictail/resource/base.py
tictail/resource/definitions.py