Metadata-Version: 1.1
Name: tictail
Version: 0.2.2
Summary: Python bindings for the Tictail API
Home-page: https://github.com/tictail/tictail-python
Author: Tictail AB
Author-email: tech@tictail.com
License: MIT
Download-URL: https://github.com/tictail/tictail-python/releases
Keywords: tictail,rest,api
Platform: UNKNOWN
Classifier: Development Status :: 4 - Beta
Classifier: Intended Audience :: Developers
Classifier: License :: OSI Approved :: MIT License
Classifier: Operating System :: OS Independent
Classifier: Programming Language :: Python
Classifier: Programming Language :: Python :: 2
Classifier: Programming Language :: Python :: 2.6
Classifier: Topic :: Software Development :: Libraries
